fourth/__init__.py
fourth/_internal.py
fourth/types.py
fourth-0.0.10.dist-info/LICENSE
fourth-0.0.10.dist-info/METADATA
fourth-0.0.10.dist-info/WHEEL
fourth-0.0.10.dist-info/top_level.txt
fourth-0.0.10.dist-info/RECORD
